<?xml version="1.0" encoding="ISO-8859-1"?>
<ConteudoXML>
  <Texto conteudo="Se a eleição fosse hoje , o presidente Luiz_Inácio_Lula_da_Silva , candidato a a reeleição , teria 44 % de as intenções de voto , contra 25 % de o tucano Geraldo_Alckmin , de acordo com a pesquisa CNI/Ibope divulgada em esta sexta-feira . Heloísa_Helena , candidata a a Presidência por o PSOL , aparece em terceiro , com 11 % de as intenções de voto , seguida por Cristovam_Buarque ( PDT ) e Luciano_Bivar ( PSL ) , ambos com 1 % . José_Maria_Eymael , de o PSDC , e Rui_Pimenta , de o PCO , não chegaram a obter 1 % de as intenções de voto . Considerando apenas os votos válidos , Lula venceria as eleições de outubro ainda em o primeiro turno . Não é possível fazer uma comparação entre a pesquisa divulgada hoje e a anterior , porque esta é a primeira CNI/Ibope com a lista oficial de os candidatos de o TSE ( Tribunal_Superior_Eleitoral ) a a sucessão presidencial . A pesquisa de hoje apresentou uma variação em a lista espontânea ( quando os entrevistados dizem em quem pretendem votar sem um cartão com nomes ) . em este cenário , Lula sobe de 27 % para 31 % e Alckmin passa de 4 % para 14 % ; Heloísa também cresce , de 1 % para 6 % . De_acordo com a CNI/Ibope , em um possível segundo turno , Lula perderia 10 pontos de vantagem para Alckmin . Em junho , o presidente tinha 53 % de as intenções de voto contra 29 % de o tucano . Agora , Lula teria 50 % , contra 36 % de Alckmin . em um eventual segundo turno com Heloísa_Helena , a vantagem de Lula também cairia , de_acordo com a pesquisa de hoje . O presidente teria 53 % de as intenções de voto contra 30 % de Heloísa . Em junho , Lula tinha 57 % e Heloísa 21 % . A pesquisa ouviu 2.002 pessoas entre os dias 29 e 31 de julho , em 142 municípios de o país . A margem de erro é de dois pontos percentuais , para mais ou para menos . em a comparação com a pesquisa Ibope divulgada há nove dias , Lula permaneceu estável em 44 % e Alckmin oscilou dois pontos percentuais , de 27 % para 25 % . Já Heloísa subiu três pontos , de 8 % para 11 % . em um eventual segundo turno e em a comparação com a pesquisa Ibope de o dia 25 , Lula oscila de 48 % para 50 % , enquanto Alckmin cai de 39 % para 36 % . Uma possível disputa entre Lula e Heloísa em um segundo turno não foi cogitada por o Ibope em esse levantamento de o dia 25 . Os números de a última pesquisa Datafolha são semelhantes a os divulgados em esta sexta-feira . em a pesquisa , divulgada em o último dia 19 por a Folha , Lula aparece com 44 % de as intenções de voto e Alckmin , com 28 % . A candidata de o PSOL a a Presidência vem em terceiro , com 10 % ." />
  <Sentencas>
    <sentenca_1 conteudo="Se a eleição fosse hoje, o presidente Luiz Inácio Lula de a Silva, candidato aa reeleição, teria 44% de as intenções de voto, contra 25% de o tucano Geraldo Alckmin, de acordo com a pesquisa CNI/Ibope divulgada em esta sexta-feira." />
    <sentenca_2 conteudo="Heloísa Helena, candidata aa Presidência por o PSOL, aparece em terceiro, com 11% de as intenções de voto, seguida por Cristovam Buarque (PDT) e Luciano Bivar (PSL), ambos com 1%." />
    <sentenca_3 conteudo="José Maria Eymael, de o PSDC, e Rui Pimenta, de o PCO, não chegaram a obter 1% de as intenções de voto." />
    <sentenca_4 conteudo="Considerando apenas os votos válidos, Lula venceria as eleições de outubro ainda em o primeiro turno." />
    <sentenca_5 conteudo="Não é possível fazer uma comparação entre a pesquisa divulgada hoje e a anterior, porque esta é a primeira CNI/Ibope com a lista oficial de os candidatos de o TSE (Tribunal Superior Eleitoral) aa sucessão presidencial." />
    <sentenca_6 conteudo="A pesquisa de hoje apresentou uma variação em a lista espontânea (quando os entrevistados dizem em quem pretendem votar sem um cartão com nomes)." />
    <sentenca_7 conteudo="Neste cenário, Lula sobe de 27% para 31% e Alckmin passa de 4% para 14%;" />
    <sentenca_8 conteudo="Heloísa também cresce, de 1% para 6%." />
    <sentenca_9 conteudo="De acordo com a CNI/Ibope, num possível segundo turno, Lula perderia 10 pontos de vantagem para Alckmin." />
    <sentenca_10 conteudo="Em junho, o presidente tinha 53% de as intenções de voto contra 29% de o tucano." />
    <sentenca_11 conteudo="Agora, Lula teria 50%, contra 36% de Alckmin." />
    <sentenca_12 conteudo="Num eventual segundo turno com Heloísa Helena, a vantagem de Lula também cairia, de acordo com a pesquisa de hoje." />
    <sentenca_13 conteudo="O presidente teria 53% de as intenções de voto contra 30% de Heloísa." />
    <sentenca_14 conteudo="Em junho, Lula tinha 57% e Heloísa 21%." />
    <sentenca_15 conteudo="A pesquisa ouviu 2.002 pessoas entre os dias 29 e 31 de julho, em 142 municípios de o país." />
    <sentenca_16 conteudo="A margem de erro é de dois pontos percentuais, para mais ou para menos." />
    <sentenca_17 conteudo="Na comparação com a pesquisa Ibope divulgada há nove dias, Lula permaneceu estável em 44% e Alckmin oscilou dois pontos percentuais, de 27% para 25%." />
    <sentenca_18 conteudo="Já Heloísa subiu três pontos, de 8% para 11%." />
    <sentenca_19 conteudo="Num eventual segundo turno e em a comparação com a pesquisa Ibope de o dia 25, Lula oscila de 48% para 50%, enquanto Alckmin cai de 39% para 36%." />
    <sentenca_20 conteudo="Uma possível disputa entre Lula e Heloísa num segundo turno não foi cogitada por o Ibope em esse levantamento de o dia 25." />
    <sentenca_21 conteudo="Os números de a última pesquisa Datafolha são semelhantes aos divulgados em esta sexta-feira." />
    <sentenca_22 conteudo="Na pesquisa, divulgada em o último dia 19 por a Folha, Lula aparece com 44% de as intenções de voto e Alckmin, com 28%." />
    <sentenca_23 conteudo="A candidata de o PSOL aa Presidência vem em terceiro, com 10%." />
  </Sentencas>
  <Tokens>
    <word_0 token="Se" lemma="se" pos="conj-s" features="-" sentenca="1" />
    <word_1 token="a" lemma="o" pos="art" features="F=S" sentenca="1" />
    <word_2 token="eleição" lemma="eleição" pos="n" features="F=S" sentenca="1" />
    <word_3 token="fosse" lemma="fossar, ir, ser" pos="v-fin" features="IMPF=3S=SUBJ" sentenca="1" />
    <word_4 token="hoje" lemma="hoje" pos="adv" features="-" sentenca="1" />
    <word_5 token="," lemma="" pos="," features="-" sentenca="1" />
    <word_6 token="o" lemma="o" pos="art" features="M=S" sentenca="1" />
    <word_7 token="presidente" lemma="presidente" pos="n" features="M=S" sentenca="1" />
    <word_8 token="Luiz_Inácio_Lula_da_Silva" lemma="" pos="prop" features="M=S" sentenca="1" />
    <word_9 token="," lemma="" pos="," features="-" sentenca="1" />
    <word_10 token="candidato" lemma="candidato" pos="n" features="M=S" sentenca="1" />
    <word_11 token="a" lemma="a" pos="prp" features="-" sentenca="1" />
    <word_12 token="a" lemma="o" pos="art" features="F=S" sentenca="1" />
    <word_13 token="reeleição" lemma="eleição" pos="n" features="F=S" sentenca="1" />
    <word_14 token="," lemma="" pos="," features="-" sentenca="1" />
    <word_15 token="teria" lemma="ter" pos="v-fin" features="COND=3S" sentenca="1" />
    <word_16 token="44" lemma="" pos="num" features="M=P" sentenca="1" />
    <word_17 token="%" lemma="" pos="n" features="M=P" sentenca="1" />
    <word_18 token="de" lemma="de" pos="prp" features="-" sentenca="1" />
    <word_19 token="as" lemma="o" pos="art" features="F=P" sentenca="1" />
    <word_20 token="intenções" lemma="intenção" pos="n" features="F=P" sentenca="1" />
    <word_21 token="de" lemma="de" pos="prp" features="-" sentenca="1" />
    <word_22 token="voto" lemma="voto" pos="n" features="M=S" sentenca="1" />
    <word_23 token="," lemma="" pos="," features="-" sentenca="1" />
    <word_24 token="contra" lemma="contra" pos="prp" features="-" sentenca="1" />
    <word_25 token="25" lemma="" pos="num" features="M=P" sentenca="1" />
    <word_26 token="%" lemma="" pos="n" features="M=P" sentenca="1" />
    <word_27 token="de" lemma="de" pos="prp" features="-" sentenca="1" />
    <word_28 token="o" lemma="o" pos="art" features="M=S" sentenca="1" />
    <word_29 token="tucano" lemma="tucano" pos="n" features="M=S" sentenca="1" />
    <word_30 token="Geraldo_Alckmin" lemma="" pos="prop" features="M=S" sentenca="1" />
    <word_31 token="," lemma="" pos="," features="-" sentenca="1" />
    <word_32 token="de" lemma="de" pos="prp" features="-" sentenca="1" />
    <word_33 token="acordo" lemma="acordo" pos="n" features="M=S" sentenca="1" />
    <word_34 token="com" lemma="com" pos="prp" features="-" sentenca="1" />
    <word_35 token="a" lemma="o" pos="art" features="F=S" sentenca="1" />
    <word_36 token="pesquisa" lemma="pesquisa" pos="n" features="F=S" sentenca="1" />
    <word_37 token="CNI/Ibope" lemma="" pos="prop" features="F=S" sentenca="1" />
    <word_38 token="divulgada" lemma="divulgar" pos="v-pcp" features="F=S" sentenca="1" />
    <word_39 token="em" lemma="em" pos="prp" features="-" sentenca="1" />
    <word_40 token="esta" lemma="este" pos="pron-det" features="F=S" sentenca="1" />
    <word_41 token="sexta-feira" lemma="sexta-feira" pos="n" features="F=S" sentenca="1" />
    <word_42 token="." lemma="." pos="." features="-" sentenca="1" />
    <word_43 token="Heloísa_Helena" lemma="" pos="prop" features="F=S" sentenca="2" />
    <word_44 token="," lemma="" pos="," features="-" sentenca="2" />
    <word_45 token="candidata" lemma="candidato" pos="n" features="F=S" sentenca="2" />
    <word_46 token="a" lemma="a" pos="prp" features="-" sentenca="2" />
    <word_47 token="a" lemma="o" pos="art" features="F=S" sentenca="2" />
    <word_48 token="Presidência" lemma="presidência" pos="n" features="F=S" sentenca="2" />
    <word_49 token="por" lemma="por" pos="prp" features="-" sentenca="2" />
    <word_50 token="o" lemma="o" pos="art" features="M=S" sentenca="2" />
    <word_51 token="PSOL" lemma="" pos="prop" features="M=S" sentenca="2" />
    <word_52 token="," lemma="" pos="," features="-" sentenca="2" />
    <word_53 token="aparece" lemma="aparecer" pos="v-fin" features="PR=3S=IND" sentenca="2" />
    <word_54 token="em" lemma="em" pos="prp" features="-" sentenca="2" />
    <word_55 token="terceiro" lemma="" pos="adj" features="M=S" sentenca="2" />
    <word_56 token="," lemma="" pos="," features="-" sentenca="2" />
    <word_57 token="com" lemma="com" pos="prp" features="-" sentenca="2" />
    <word_58 token="11" lemma="" pos="num" features="M=P" sentenca="2" />
    <word_59 token="%" lemma="" pos="n" features="M=P" sentenca="2" />
    <word_60 token="de" lemma="de" pos="prp" features="-" sentenca="2" />
    <word_61 token="as" lemma="o" pos="art" features="F=P" sentenca="2" />
    <word_62 token="intenções" lemma="intenção" pos="n" features="F=P" sentenca="2" />
    <word_63 token="de" lemma="de" pos="prp" features="-" sentenca="2" />
    <word_64 token="voto" lemma="voto" pos="n" features="M=S" sentenca="2" />
    <word_65 token="," lemma="" pos="," features="-" sentenca="2" />
    <word_66 token="seguida" lemma="seguir" pos="v-pcp" features="F=S" sentenca="2" />
    <word_67 token="por" lemma="por" pos="prp" features="-" sentenca="2" />
    <word_68 token="Cristovam_Buarque" lemma="" pos="prop" features="M=S" sentenca="2" />
    <word_69 token="(" lemma="(" pos="(" features="-" sentenca="2" />
    <word_70 token="PDT" lemma="" pos="prop" features="M=S" sentenca="2" />
    <word_71 token=")" lemma=")" pos=")" features="-" sentenca="2" />
    <word_72 token="e" lemma="e" pos="conj-c" features="-" sentenca="2" />
    <word_73 token="Luciano_Bivar" lemma="" pos="prop" features="M=S" sentenca="2" />
    <word_74 token="(" lemma="(" pos="(" features="-" sentenca="2" />
    <word_75 token="PSL" lemma="" pos="prop" features="M=S" sentenca="2" />
    <word_76 token=")" lemma=")" pos=")" features="-" sentenca="2" />
    <word_77 token="," lemma="" pos="," features="-" sentenca="2" />
    <word_78 token="ambos" lemma="ambos" pos="pron-det" features="M=P" sentenca="2" />
    <word_79 token="com" lemma="com" pos="prp" features="-" sentenca="2" />
    <word_80 token="1" lemma="" pos="num" features="M=S" sentenca="2" />
    <word_81 token="%" lemma="" pos="n" features="M=P" sentenca="2" />
    <word_82 token="." lemma="." pos="." features="-" sentenca="2" />
    <word_83 token="José_Maria_Eymael" lemma="" pos="prop" features="M=S" sentenca="3" />
    <word_84 token="," lemma="" pos="," features="-" sentenca="3" />
    <word_85 token="de" lemma="de" pos="prp" features="-" sentenca="3" />
    <word_86 token="o" lemma="o" pos="art" features="M=S" sentenca="3" />
    <word_87 token="PSDC" lemma="" pos="prop" features="M=S" sentenca="3" />
    <word_88 token="," lemma="" pos="," features="-" sentenca="3" />
    <word_89 token="e" lemma="e" pos="conj-c" features="-" sentenca="3" />
    <word_90 token="Rui_Pimenta" lemma="" pos="prop" features="M=S" sentenca="3" />
    <word_91 token="," lemma="" pos="," features="-" sentenca="3" />
    <word_92 token="de" lemma="de" pos="prp" features="-" sentenca="3" />
    <word_93 token="o" lemma="o" pos="art" features="M=S" sentenca="3" />
    <word_94 token="PCO" lemma="" pos="prop" features="M=S" sentenca="3" />
    <word_95 token="," lemma="" pos="," features="-" sentenca="3" />
    <word_96 token="não" lemma="não" pos="adv" features="-" sentenca="3" />
    <word_97 token="chegaram" lemma="chegar" pos="v-fin" features="PS=3P=IND" sentenca="3" />
    <word_98 token="a" lemma="a" pos="prp" features="-" sentenca="3" />
    <word_99 token="obter" lemma="obter" pos="v-inf" features="-" sentenca="3" />
    <word_100 token="1" lemma="" pos="num" features="M=S" sentenca="3" />
    <word_101 token="%" lemma="" pos="n" features="M=P" sentenca="3" />
    <word_102 token="de" lemma="de" pos="prp" features="-" sentenca="3" />
    <word_103 token="as" lemma="o" pos="art" features="F=P" sentenca="3" />
    <word_104 token="intenções" lemma="intenção" pos="n" features="F=P" sentenca="3" />
    <word_105 token="de" lemma="de" pos="prp" features="-" sentenca="3" />
    <word_106 token="voto" lemma="voto" pos="n" features="M=S" sentenca="3" />
    <word_107 token="." lemma="." pos="." features="-" sentenca="3" />
    <word_108 token="Considerando" lemma="considerar" pos="v-ger" features="-" sentenca="4" />
    <word_109 token="apenas" lemma="apenas" pos="adv" features="-" sentenca="4" />
    <word_110 token="os" lemma="o" pos="art" features="M=P" sentenca="4" />
    <word_111 token="votos" lemma="voto" pos="n" features="M=P" sentenca="4" />
    <word_112 token="válidos" lemma="válido" pos="adj" features="M=P" sentenca="4" />
    <word_113 token="," lemma="" pos="," features="-" sentenca="4" />
    <word_114 token="Lula" lemma="Lula" pos="prop" features="-" sentenca="4" />
    <word_115 token="venceria" lemma="vencer" pos="v-fin" features="COND=3S" sentenca="4" />
    <word_116 token="as" lemma="o" pos="art" features="F=P" sentenca="4" />
    <word_117 token="eleições" lemma="eleição" pos="n" features="F=P" sentenca="4" />
    <word_118 token="de" lemma="de" pos="prp" features="-" sentenca="4" />
    <word_119 token="outubro" lemma="outubro" pos="n" features="M=S" sentenca="4" />
    <word_120 token="ainda" lemma="ainda" pos="adv" features="-" sentenca="4" />
    <word_121 token="em" lemma="em" pos="prp" features="-" sentenca="4" />
    <word_122 token="o" lemma="o" pos="art" features="M=S" sentenca="4" />
    <word_123 token="primeiro" lemma="primeiro" pos="adj" features="M=S" sentenca="4" />
    <word_124 token="turno" lemma="turno" pos="n" features="M=S" sentenca="4" />
    <word_125 token="." lemma="." pos="." features="-" sentenca="4" />
    <word_126 token="Não" lemma="não" pos="adv" features="-" sentenca="5" />
    <word_127 token="é" lemma="ser" pos="v-fin" features="PR=3S=IND" sentenca="5" />
    <word_128 token="possível" lemma="possível" pos="adj" features="M=S" sentenca="5" />
    <word_129 token="fazer" lemma="fazer" pos="v-inf" features="-" sentenca="5" />
    <word_130 token="uma" lemma="um" pos="art" features="F=S" sentenca="5" />
    <word_131 token="comparação" lemma="comparação, comparar" pos="n" features="F=S" sentenca="5" />
    <word_132 token="entre" lemma="entre" pos="prp" features="-" sentenca="5" />
    <word_133 token="a" lemma="o" pos="art" features="F=S" sentenca="5" />
    <word_134 token="pesquisa" lemma="pesquisa" pos="n" features="F=S" sentenca="5" />
    <word_135 token="divulgada" lemma="divulgar" pos="v-pcp" features="F=S" sentenca="5" />
    <word_136 token="hoje" lemma="hoje" pos="adv" features="-" sentenca="5" />
    <word_137 token="e" lemma="e" pos="conj-c" features="-" sentenca="5" />
    <word_138 token="a" lemma="o" pos="art" features="F=S" sentenca="5" />
    <word_139 token="anterior" lemma="anterior" pos="adj" features="F=S" sentenca="5" />
    <word_140 token="," lemma="" pos="," features="-" sentenca="5" />
    <word_141 token="porque" lemma="porque" pos="conj-s" features="-" sentenca="5" />
    <word_142 token="esta" lemma="este" pos="pron-det" features="F=S" sentenca="5" />
    <word_143 token="é" lemma="ser" pos="v-fin" features="PR=3S=IND" sentenca="5" />
    <word_144 token="a" lemma="o" pos="art" features="F=S" sentenca="5" />
    <word_145 token="primeira" lemma="" pos="adj" features="F=S" sentenca="5" />
    <word_146 token="CNI/Ibope" lemma="" pos="prop" features="M=S" sentenca="5" />
    <word_147 token="com" lemma="com" pos="prp" features="-" sentenca="5" />
    <word_148 token="a" lemma="o" pos="art" features="F=S" sentenca="5" />
    <word_149 token="lista" lemma="lista" pos="n" features="F=S" sentenca="5" />
    <word_150 token="oficial" lemma="oficial" pos="adj" features="F=S" sentenca="5" />
    <word_151 token="de" lemma="de" pos="prp" features="-" sentenca="5" />
    <word_152 token="os" lemma="o" pos="art" features="M=P" sentenca="5" />
    <word_153 token="candidatos" lemma="candidato" pos="n" features="M=P" sentenca="5" />
    <word_154 token="de" lemma="de" pos="prp" features="-" sentenca="5" />
    <word_155 token="o" lemma="o" pos="art" features="M=S" sentenca="5" />
    <word_156 token="TSE" lemma="" pos="prop" features="M=S" sentenca="5" />
    <word_157 token="(" lemma="(" pos="(" features="-" sentenca="5" />
    <word_158 token="Tribunal_Superior_Eleitoral" lemma="" pos="prop" features="M=S" sentenca="5" />
    <word_159 token=")" lemma=")" pos=")" features="-" sentenca="5" />
    <word_160 token="a" lemma="a" pos="prp" features="-" sentenca="5" />
    <word_161 token="a" lemma="o" pos="art" features="F=S" sentenca="5" />
    <word_162 token="sucessão" lemma="sucessão" pos="n" features="F=S" sentenca="5" />
    <word_163 token="presidencial" lemma="presidencial" pos="adj" features="F=S" sentenca="5" />
    <word_164 token="." lemma="." pos="." features="-" sentenca="5" />
    <word_165 token="A" lemma="o" pos="art" features="F=S" sentenca="6" />
    <word_166 token="pesquisa" lemma="pesquisa" pos="n" features="F=S" sentenca="6" />
    <word_167 token="de" lemma="de" pos="prp" features="-" sentenca="6" />
    <word_168 token="hoje" lemma="hoje" pos="adv" features="-" sentenca="6" />
    <word_169 token="apresentou" lemma="apresentar" pos="v-fin" features="PS=3S=IND" sentenca="6" />
    <word_170 token="uma" lemma="um" pos="art" features="F=S" sentenca="6" />
    <word_171 token="variação" lemma="variação, variar" pos="n" features="F=S" sentenca="6" />
    <word_172 token="em" lemma="em" pos="prp" features="-" sentenca="6" />
    <word_173 token="a" lemma="o" pos="art" features="F=S" sentenca="6" />
    <word_174 token="lista" lemma="lista" pos="n" features="F=S" sentenca="6" />
    <word_175 token="espontânea" lemma="espontâneo" pos="adj" features="F=S" sentenca="6" />
    <word_176 token="(" lemma="(" pos="(" features="-" sentenca="6" />
    <word_177 token="quando" lemma="quando" pos="adv" features="-" sentenca="6" />
    <word_178 token="os" lemma="o" pos="art" features="M=P" sentenca="6" />
    <word_179 token="entrevistados" lemma="entrevistar" pos="v-pcp" features="M=P" sentenca="6" />
    <word_180 token="dizem" lemma="dizer" pos="v-fin" features="PR=3P=IND" sentenca="6" />
    <word_181 token="em" lemma="em" pos="prp" features="-" sentenca="6" />
    <word_182 token="quem" lemma="quem" pos="pron-indp" features="M/F=S" sentenca="6" />
    <word_183 token="pretendem" lemma="pretender" pos="v-fin" features="PR=3P=IND" sentenca="6" />
    <word_184 token="votar" lemma="votar" pos="v-inf" features="-" sentenca="6" />
    <word_185 token="sem" lemma="sem" pos="prp" features="-" sentenca="6" />
    <word_186 token="um" lemma="um" pos="art" features="M=S" sentenca="6" />
    <word_187 token="cartão" lemma="cartão" pos="n" features="M=S" sentenca="6" />
    <word_188 token="com" lemma="com" pos="prp" features="-" sentenca="6" />
    <word_189 token="nomes" lemma="nome" pos="n" features="M=P" sentenca="6" />
    <word_190 token=")" lemma=")" pos=")" features="-" sentenca="6" />
    <word_191 token="." lemma="." pos="." features="-" sentenca="6" />
    <word_192 token="em" lemma="em" pos="prp" features="-" sentenca="7" />
    <word_193 token="este" lemma="este" pos="pron-det" features="M=S" sentenca="7" />
    <word_194 token="cenário" lemma="cenário" pos="n" features="M=S" sentenca="7" />
    <word_195 token="," lemma="" pos="," features="-" sentenca="7" />
    <word_196 token="Lula" lemma="Lula" pos="prop" features="-" sentenca="7" />
    <word_197 token="sobe" lemma="subir" pos="v-fin" features="PR=3S=IND" sentenca="7" />
    <word_198 token="de" lemma="de" pos="prp" features="-" sentenca="7" />
    <word_199 token="27" lemma="" pos="num" features="M=P" sentenca="7" />
    <word_200 token="%" lemma="" pos="n" features="M=P" sentenca="7" />
    <word_201 token="para" lemma="para" pos="prp" features="-" sentenca="7" />
    <word_202 token="31" lemma="" pos="num" features="M=P" sentenca="7" />
    <word_203 token="%" lemma="" pos="n" features="M=P" sentenca="7" />
    <word_204 token="e" lemma="e" pos="conj-c" features="-" sentenca="7" />
    <word_205 token="Alckmin" lemma="" pos="prop" features="M=S" sentenca="7" />
    <word_206 token="passa" lemma="passar" pos="v-fin" features="PR=3S=IND" sentenca="7" />
    <word_207 token="de" lemma="de" pos="prp" features="-" sentenca="7" />
    <word_208 token="4" lemma="" pos="num" features="M=P" sentenca="7" />
    <word_209 token="%" lemma="" pos="n" features="M=P" sentenca="7" />
    <word_210 token="para" lemma="para" pos="prp" features="-" sentenca="7" />
    <word_211 token="14" lemma="" pos="num" features="M=P" sentenca="7" />
    <word_212 token="%" lemma="" pos="n" features="M=P" sentenca="7" />
    <word_213 token=";" lemma=";" pos=";" features="-" sentenca="7" />
    <word_214 token="Heloísa" lemma="" pos="prop" features="F=S" sentenca="8" />
    <word_215 token="também" lemma="também" pos="adv" features="-" sentenca="8" />
    <word_216 token="cresce" lemma="crescer" pos="v-fin" features="PR=3S=IND" sentenca="8" />
    <word_217 token="," lemma="" pos="," features="-" sentenca="8" />
    <word_218 token="de" lemma="de" pos="prp" features="-" sentenca="8" />
    <word_219 token="1" lemma="" pos="num" features="M=S" sentenca="8" />
    <word_220 token="%" lemma="" pos="n" features="M=P" sentenca="8" />
    <word_221 token="para" lemma="para" pos="prp" features="-" sentenca="8" />
    <word_222 token="6" lemma="" pos="num" features="M=P" sentenca="8" />
    <word_223 token="%" lemma="" pos="n" features="M=P" sentenca="8" />
    <word_224 token="." lemma="." pos="." features="-" sentenca="8" />
    <word_225 token="De_acordo" lemma="" pos="adv" features="-" sentenca="9" />
    <word_226 token="com" lemma="com" pos="prp" features="-" sentenca="9" />
    <word_227 token="a" lemma="o" pos="art" features="F=S" sentenca="9" />
    <word_228 token="CNI/Ibope" lemma="" pos="prop" features="F=S" sentenca="9" />
    <word_229 token="," lemma="" pos="," features="-" sentenca="9" />
    <word_230 token="em" lemma="em" pos="prp" features="-" sentenca="9" />
    <word_231 token="um" lemma="um" pos="art" features="M=S" sentenca="9" />
    <word_232 token="possível" lemma="possível" pos="adj" features="M=S" sentenca="9" />
    <word_233 token="segundo" lemma="" pos="adj" features="M=S" sentenca="9" />
    <word_234 token="turno" lemma="turno" pos="n" features="M=S" sentenca="9" />
    <word_235 token="," lemma="" pos="," features="-" sentenca="9" />
    <word_236 token="Lula" lemma="Lula" pos="prop" features="-" sentenca="9" />
    <word_237 token="perderia" lemma="perder" pos="v-fin" features="COND=3S" sentenca="9" />
    <word_238 token="10" lemma="" pos="num" features="M=P" sentenca="9" />
    <word_239 token="pontos" lemma="ponto" pos="n" features="M=P" sentenca="9" />
    <word_240 token="de" lemma="de" pos="prp" features="-" sentenca="9" />
    <word_241 token="vantagem" lemma="vantagem" pos="n" features="F=S" sentenca="9" />
    <word_242 token="para" lemma="para" pos="prp" features="-" sentenca="9" />
    <word_243 token="Alckmin" lemma="" pos="prop" features="M=S" sentenca="9" />
    <word_244 token="." lemma="." pos="." features="-" sentenca="9" />
    <word_245 token="Em" lemma="em" pos="prp" features="-" sentenca="10" />
    <word_246 token="junho" lemma="junho" pos="n" features="M=S" sentenca="10" />
    <word_247 token="," lemma="" pos="," features="-" sentenca="10" />
    <word_248 token="o" lemma="o" pos="art" features="M=S" sentenca="10" />
    <word_249 token="presidente" lemma="presidente" pos="n" features="M=S" sentenca="10" />
    <word_250 token="tinha" lemma="ter" pos="v-fin" features="IMPF=3S=IND" sentenca="10" />
    <word_251 token="53" lemma="" pos="num" features="M=P" sentenca="10" />
    <word_252 token="%" lemma="" pos="n" features="M=P" sentenca="10" />
    <word_253 token="de" lemma="de" pos="prp" features="-" sentenca="10" />
    <word_254 token="as" lemma="o" pos="art" features="F=P" sentenca="10" />
    <word_255 token="intenções" lemma="intenção" pos="n" features="F=P" sentenca="10" />
    <word_256 token="de" lemma="de" pos="prp" features="-" sentenca="10" />
    <word_257 token="voto" lemma="voto" pos="n" features="M=S" sentenca="10" />
    <word_258 token="contra" lemma="contra" pos="prp" features="-" sentenca="10" />
    <word_259 token="29" lemma="" pos="num" features="M=P" sentenca="10" />
    <word_260 token="%" lemma="" pos="n" features="M=P" sentenca="10" />
    <word_261 token="de" lemma="de" pos="prp" features="-" sentenca="10" />
    <word_262 token="o" lemma="o" pos="art" features="M=S" sentenca="10" />
    <word_263 token="tucano" lemma="tucano" pos="n" features="M=S" sentenca="10" />
    <word_264 token="." lemma="." pos="." features="-" sentenca="10" />
    <word_265 token="Agora" lemma="agora" pos="adv" features="-" sentenca="11" />
    <word_266 token="," lemma="" pos="," features="-" sentenca="11" />
    <word_267 token="Lula" lemma="Lula" pos="prop" features="-" sentenca="11" />
    <word_268 token="teria" lemma="ter" pos="v-fin" features="COND=3S" sentenca="11" />
    <word_269 token="50" lemma="" pos="num" features="M=P" sentenca="11" />
    <word_270 token="%" lemma="" pos="n" features="M=P" sentenca="11" />
    <word_271 token="," lemma="" pos="," features="-" sentenca="11" />
    <word_272 token="contra" lemma="contra" pos="prp" features="-" sentenca="11" />
    <word_273 token="36" lemma="" pos="num" features="M=P" sentenca="11" />
    <word_274 token="%" lemma="" pos="n" features="M=P" sentenca="11" />
    <word_275 token="de" lemma="de" pos="prp" features="-" sentenca="11" />
    <word_276 token="Alckmin" lemma="" pos="prop" features="M=S" sentenca="11" />
    <word_277 token="." lemma="." pos="." features="-" sentenca="11" />
    <word_278 token="em" lemma="em" pos="prp" features="-" sentenca="12" />
    <word_279 token="um" lemma="um" pos="art" features="M=S" sentenca="12" />
    <word_280 token="eventual" lemma="eventual" pos="adj" features="M=S" sentenca="12" />
    <word_281 token="segundo" lemma="segundo" pos="prp" features="-" sentenca="12" />
    <word_282 token="turno" lemma="turno" pos="n" features="M=S" sentenca="12" />
    <word_283 token="com" lemma="com" pos="prp" features="-" sentenca="12" />
    <word_284 token="Heloísa_Helena" lemma="" pos="prop" features="M=S" sentenca="12" />
    <word_285 token="," lemma="" pos="," features="-" sentenca="12" />
    <word_286 token="a" lemma="o" pos="art" features="F=S" sentenca="12" />
    <word_287 token="vantagem" lemma="vantagem" pos="n" features="F=S" sentenca="12" />
    <word_288 token="de" lemma="de" pos="prp" features="-" sentenca="12" />
    <word_289 token="Lula" lemma="Lula" pos="prop" features="-" sentenca="12" />
    <word_290 token="também" lemma="também" pos="adv" features="-" sentenca="12" />
    <word_291 token="cairia" lemma="cair" pos="v-fin" features="COND=3S" sentenca="12" />
    <word_292 token="," lemma="" pos="," features="-" sentenca="12" />
    <word_293 token="de_acordo" lemma="" pos="adv" features="-" sentenca="12" />
    <word_294 token="com" lemma="com" pos="prp" features="-" sentenca="12" />
    <word_295 token="a" lemma="o" pos="art" features="F=S" sentenca="12" />
    <word_296 token="pesquisa" lemma="pesquisa" pos="n" features="F=S" sentenca="12" />
    <word_297 token="de" lemma="de" pos="prp" features="-" sentenca="12" />
    <word_298 token="hoje" lemma="hoje" pos="adv" features="-" sentenca="12" />
    <word_299 token="." lemma="." pos="." features="-" sentenca="12" />
    <word_300 token="O" lemma="o" pos="art" features="M=S" sentenca="13" />
    <word_301 token="presidente" lemma="presidente" pos="n" features="M=S" sentenca="13" />
    <word_302 token="teria" lemma="ter" pos="v-fin" features="COND=3S" sentenca="13" />
    <word_303 token="53" lemma="" pos="num" features="M=P" sentenca="13" />
    <word_304 token="%" lemma="" pos="n" features="M=P" sentenca="13" />
    <word_305 token="de" lemma="de" pos="prp" features="-" sentenca="13" />
    <word_306 token="as" lemma="o" pos="art" features="F=P" sentenca="13" />
    <word_307 token="intenções" lemma="intenção" pos="n" features="F=P" sentenca="13" />
    <word_308 token="de" lemma="de" pos="prp" features="-" sentenca="13" />
    <word_309 token="voto" lemma="voto" pos="n" features="M=S" sentenca="13" />
    <word_310 token="contra" lemma="contra" pos="prp" features="-" sentenca="13" />
    <word_311 token="30" lemma="" pos="num" features="M=P" sentenca="13" />
    <word_312 token="%" lemma="" pos="n" features="M=P" sentenca="13" />
    <word_313 token="de" lemma="de" pos="prp" features="-" sentenca="13" />
    <word_314 token="Heloísa" lemma="" pos="prop" features="M=S" sentenca="13" />
    <word_315 token="." lemma="." pos="." features="-" sentenca="13" />
    <word_316 token="Em" lemma="em" pos="prp" features="-" sentenca="14" />
    <word_317 token="junho" lemma="junho" pos="n" features="M=S" sentenca="14" />
    <word_318 token="," lemma="" pos="," features="-" sentenca="14" />
    <word_319 token="Lula" lemma="Lula" pos="prop" features="-" sentenca="14" />
    <word_320 token="tinha" lemma="ter" pos="v-fin" features="IMPF=3S=IND" sentenca="14" />
    <word_321 token="57" lemma="" pos="num" features="M=P" sentenca="14" />
    <word_322 token="%" lemma="" pos="n" features="M=P" sentenca="14" />
    <word_323 token="e" lemma="e" pos="conj-c" features="-" sentenca="14" />
    <word_324 token="Heloísa" lemma="" pos="prop" features="F=S" sentenca="14" />
    <word_325 token="21" lemma="" pos="num" features="M=P" sentenca="14" />
    <word_326 token="%" lemma="" pos="n" features="M=P" sentenca="14" />
    <word_327 token="." lemma="." pos="." features="-" sentenca="14" />
    <word_328 token="A" lemma="o" pos="art" features="F=S" sentenca="15" />
    <word_329 token="pesquisa" lemma="pesquisa" pos="n" features="F=S" sentenca="15" />
    <word_330 token="ouviu" lemma="ouvir" pos="v-fin" features="PS=3S=IND" sentenca="15" />
    <word_331 token="2.002" lemma="" pos="num" features="F=P" sentenca="15" />
    <word_332 token="pessoas" lemma="pessoa" pos="n" features="F=P" sentenca="15" />
    <word_333 token="entre" lemma="entre" pos="prp" features="-" sentenca="15" />
    <word_334 token="os" lemma="o" pos="art" features="M=P" sentenca="15" />
    <word_335 token="dias" lemma="dia" pos="n" features="M=P" sentenca="15" />
    <word_336 token="29" lemma="" pos="num" features="M=P" sentenca="15" />
    <word_337 token="e" lemma="e" pos="conj-c" features="-" sentenca="15" />
    <word_338 token="31" lemma="" pos="num" features="M=P" sentenca="15" />
    <word_339 token="de" lemma="de" pos="prp" features="-" sentenca="15" />
    <word_340 token="julho" lemma="julho" pos="n" features="M=S" sentenca="15" />
    <word_341 token="," lemma="" pos="," features="-" sentenca="15" />
    <word_342 token="em" lemma="em" pos="prp" features="-" sentenca="15" />
    <word_343 token="142" lemma="" pos="num" features="M=P" sentenca="15" />
    <word_344 token="municípios" lemma="município" pos="n" features="M=P" sentenca="15" />
    <word_345 token="de" lemma="de" pos="prp" features="-" sentenca="15" />
    <word_346 token="o" lemma="o" pos="art" features="M=S" sentenca="15" />
    <word_347 token="país" lemma="país" pos="n" features="M=S" sentenca="15" />
    <word_348 token="." lemma="." pos="." features="-" sentenca="15" />
    <word_349 token="A" lemma="o" pos="art" features="F=S" sentenca="16" />
    <word_350 token="margem" lemma="margem" pos="n" features="F=S" sentenca="16" />
    <word_351 token="de" lemma="de" pos="prp" features="-" sentenca="16" />
    <word_352 token="erro" lemma="erro" pos="n" features="M=S" sentenca="16" />
    <word_353 token="é" lemma="ser" pos="v-fin" features="PR=3S=IND" sentenca="16" />
    <word_354 token="de" lemma="de" pos="prp" features="-" sentenca="16" />
    <word_355 token="dois" lemma="dois" pos="num" features="M=P" sentenca="16" />
    <word_356 token="pontos" lemma="ponto" pos="n" features="M=P" sentenca="16" />
    <word_357 token="percentuais" lemma="percentual" pos="adj" features="M=P" sentenca="16" />
    <word_358 token="," lemma="" pos="," features="-" sentenca="16" />
    <word_359 token="para" lemma="para" pos="prp" features="-" sentenca="16" />
    <word_360 token="mais" lemma="mais" pos="adv" features="-" sentenca="16" />
    <word_361 token="ou" lemma="ou" pos="conj-c" features="-" sentenca="16" />
    <word_362 token="para" lemma="para" pos="prp" features="-" sentenca="16" />
    <word_363 token="menos" lemma="menos" pos="pron-det" features="M=P" sentenca="16" />
    <word_364 token="." lemma="." pos="." features="-" sentenca="16" />
    <word_365 token="em" lemma="em" pos="prp" features="-" sentenca="17" />
    <word_366 token="a" lemma="o" pos="art" features="F=S" sentenca="17" />
    <word_367 token="comparação" lemma="comparação, comparar" pos="n" features="F=S" sentenca="17" />
    <word_368 token="com" lemma="com" pos="prp" features="-" sentenca="17" />
    <word_369 token="a" lemma="o" pos="art" features="F=S" sentenca="17" />
    <word_370 token="pesquisa" lemma="pesquisa" pos="n" features="F=S" sentenca="17" />
    <word_371 token="Ibope" lemma="" pos="prop" features="F=S" sentenca="17" />
    <word_372 token="divulgada" lemma="divulgar" pos="v-pcp" features="F=S" sentenca="17" />
    <word_373 token="há" lemma="" pos="prp" features="-" sentenca="17" />
    <word_374 token="nove" lemma="nove" pos="num" features="M=P" sentenca="17" />
    <word_375 token="dias" lemma="dia" pos="n" features="M=P" sentenca="17" />
    <word_376 token="," lemma="" pos="," features="-" sentenca="17" />
    <word_377 token="Lula" lemma="Lula" pos="prop" features="-" sentenca="17" />
    <word_378 token="permaneceu" lemma="permanecer" pos="v-fin" features="PS=3S=IND" sentenca="17" />
    <word_379 token="estável" lemma="estável, estar" pos="adj" features="M=S" sentenca="17" />
    <word_380 token="em" lemma="em" pos="prp" features="-" sentenca="17" />
    <word_381 token="44" lemma="" pos="num" features="M=P" sentenca="17" />
    <word_382 token="%" lemma="" pos="n" features="M=P" sentenca="17" />
    <word_383 token="e" lemma="e" pos="conj-c" features="-" sentenca="17" />
    <word_384 token="Alckmin" lemma="" pos="prop" features="F=S" sentenca="17" />
    <word_385 token="oscilou" lemma="oscilar" pos="v-fin" features="PS=3S=IND" sentenca="17" />
    <word_386 token="dois" lemma="dois" pos="num" features="M=P" sentenca="17" />
    <word_387 token="pontos" lemma="ponto" pos="n" features="M=P" sentenca="17" />
    <word_388 token="percentuais" lemma="percentual" pos="adj" features="M=P" sentenca="17" />
    <word_389 token="," lemma="" pos="," features="-" sentenca="17" />
    <word_390 token="de" lemma="de" pos="prp" features="-" sentenca="17" />
    <word_391 token="27" lemma="" pos="num" features="M=P" sentenca="17" />
    <word_392 token="%" lemma="" pos="n" features="M=P" sentenca="17" />
    <word_393 token="para" lemma="para" pos="prp" features="-" sentenca="17" />
    <word_394 token="25" lemma="" pos="num" features="M=P" sentenca="17" />
    <word_395 token="%" lemma="" pos="n" features="M=P" sentenca="17" />
    <word_396 token="." lemma="." pos="." features="-" sentenca="17" />
    <word_397 token="Já" lemma="já" pos="adv" features="-" sentenca="18" />
    <word_398 token="Heloísa" lemma="" pos="prop" features="F=S" sentenca="18" />
    <word_399 token="subiu" lemma="subir" pos="v-fin" features="PS=3S=IND" sentenca="18" />
    <word_400 token="três" lemma="três" pos="num" features="M=P" sentenca="18" />
    <word_401 token="pontos" lemma="ponto" pos="n" features="M=P" sentenca="18" />
    <word_402 token="," lemma="" pos="," features="-" sentenca="18" />
    <word_403 token="de" lemma="de" pos="prp" features="-" sentenca="18" />
    <word_404 token="8" lemma="" pos="num" features="M=P" sentenca="18" />
    <word_405 token="%" lemma="" pos="n" features="M=P" sentenca="18" />
    <word_406 token="para" lemma="para" pos="prp" features="-" sentenca="18" />
    <word_407 token="11" lemma="" pos="num" features="M=P" sentenca="18" />
    <word_408 token="%" lemma="" pos="n" features="M=P" sentenca="18" />
    <word_409 token="." lemma="." pos="." features="-" sentenca="18" />
    <word_410 token="em" lemma="em" pos="prp" features="-" sentenca="19" />
    <word_411 token="um" lemma="um" pos="art" features="M=S" sentenca="19" />
    <word_412 token="eventual" lemma="eventual" pos="adj" features="M=S" sentenca="19" />
    <word_413 token="segundo" lemma="segundo" pos="prp" features="-" sentenca="19" />
    <word_414 token="turno" lemma="turno" pos="n" features="M=S" sentenca="19" />
    <word_415 token="e" lemma="e" pos="conj-c" features="-" sentenca="19" />
    <word_416 token="em" lemma="em" pos="prp" features="-" sentenca="19" />
    <word_417 token="a" lemma="o" pos="art" features="F=S" sentenca="19" />
    <word_418 token="comparação" lemma="comparação, comparar" pos="n" features="F=S" sentenca="19" />
    <word_419 token="com" lemma="com" pos="prp" features="-" sentenca="19" />
    <word_420 token="a" lemma="o" pos="art" features="F=S" sentenca="19" />
    <word_421 token="pesquisa" lemma="pesquisa" pos="n" features="F=S" sentenca="19" />
    <word_422 token="Ibope" lemma="" pos="prop" features="F=S" sentenca="19" />
    <word_423 token="de" lemma="de" pos="prp" features="-" sentenca="19" />
    <word_424 token="o" lemma="o" pos="art" features="M=S" sentenca="19" />
    <word_425 token="dia" lemma="dia" pos="n" features="M=S" sentenca="19" />
    <word_426 token="25" lemma="" pos="num" features="M=P" sentenca="19" />
    <word_427 token="," lemma="" pos="," features="-" sentenca="19" />
    <word_428 token="Lula" lemma="Lula" pos="prop" features="-" sentenca="19" />
    <word_429 token="oscila" lemma="oscilar" pos="v-fin" features="PR=3S=IND" sentenca="19" />
    <word_430 token="de" lemma="de" pos="prp" features="-" sentenca="19" />
    <word_431 token="48" lemma="" pos="num" features="M=P" sentenca="19" />
    <word_432 token="%" lemma="" pos="n" features="M=P" sentenca="19" />
    <word_433 token="para" lemma="para" pos="prp" features="-" sentenca="19" />
    <word_434 token="50" lemma="" pos="num" features="M=P" sentenca="19" />
    <word_435 token="%" lemma="" pos="n" features="M=P" sentenca="19" />
    <word_436 token="," lemma="" pos="," features="-" sentenca="19" />
    <word_437 token="enquanto" lemma="" pos="adv" features="-" sentenca="19" />
    <word_438 token="Alckmin" lemma="" pos="prop" features="M=S" sentenca="19" />
    <word_439 token="cai" lemma="cair" pos="v-fin" features="PR=3S=IND" sentenca="19" />
    <word_440 token="de" lemma="de" pos="prp" features="-" sentenca="19" />
    <word_441 token="39" lemma="" pos="num" features="M=P" sentenca="19" />
    <word_442 token="%" lemma="" pos="n" features="M=P" sentenca="19" />
    <word_443 token="para" lemma="para" pos="prp" features="-" sentenca="19" />
    <word_444 token="36" lemma="" pos="num" features="M=P" sentenca="19" />
    <word_445 token="%" lemma="" pos="n" features="M=P" sentenca="19" />
    <word_446 token="." lemma="." pos="." features="-" sentenca="19" />
    <word_447 token="Uma" lemma="um" pos="art" features="F=S" sentenca="20" />
    <word_448 token="possível" lemma="possível" pos="adj" features="F=S" sentenca="20" />
    <word_449 token="disputa" lemma="disputa" pos="n" features="F=S" sentenca="20" />
    <word_450 token="entre" lemma="entre" pos="prp" features="-" sentenca="20" />
    <word_451 token="Lula" lemma="Lula" pos="prop" features="-" sentenca="20" />
    <word_452 token="e" lemma="e" pos="conj-c" features="-" sentenca="20" />
    <word_453 token="Heloísa" lemma="" pos="prop" features="F=S" sentenca="20" />
    <word_454 token="em" lemma="em" pos="prp" features="-" sentenca="20" />
    <word_455 token="um" lemma="um" pos="art" features="M=S" sentenca="20" />
    <word_456 token="segundo" lemma="" pos="adj" features="M=S" sentenca="20" />
    <word_457 token="turno" lemma="turno" pos="n" features="M=S" sentenca="20" />
    <word_458 token="não" lemma="não" pos="adv" features="-" sentenca="20" />
    <word_459 token="foi" lemma="ir, ser" pos="v-fin" features="PS=3S=IND" sentenca="20" />
    <word_460 token="cogitada" lemma="cogitar" pos="v-pcp" features="F=S" sentenca="20" />
    <word_461 token="por" lemma="por" pos="prp" features="-" sentenca="20" />
    <word_462 token="o" lemma="o" pos="art" features="M=S" sentenca="20" />
    <word_463 token="Ibope" lemma="" pos="prop" features="M=S" sentenca="20" />
    <word_464 token="em" lemma="em" pos="prp" features="-" sentenca="20" />
    <word_465 token="esse" lemma="esse" pos="pron-det" features="M=S" sentenca="20" />
    <word_466 token="levantamento" lemma="levantar" pos="n" features="M=S" sentenca="20" />
    <word_467 token="de" lemma="de" pos="prp" features="-" sentenca="20" />
    <word_468 token="o" lemma="o" pos="art" features="M=S" sentenca="20" />
    <word_469 token="dia" lemma="dia" pos="n" features="M=S" sentenca="20" />
    <word_470 token="25" lemma="" pos="num" features="M=P" sentenca="20" />
    <word_471 token="." lemma="." pos="." features="-" sentenca="20" />
    <word_472 token="Os" lemma="o" pos="art" features="M=P" sentenca="21" />
    <word_473 token="números" lemma="número" pos="n" features="M=P" sentenca="21" />
    <word_474 token="de" lemma="de" pos="prp" features="-" sentenca="21" />
    <word_475 token="a" lemma="o" pos="art" features="F=S" sentenca="21" />
    <word_476 token="última" lemma="último" pos="adj" features="F=S" sentenca="21" />
    <word_477 token="pesquisa" lemma="pesquisa" pos="n" features="F=S" sentenca="21" />
    <word_478 token="Datafolha" lemma="" pos="prop" features="F=S" sentenca="21" />
    <word_479 token="são" lemma="ser" pos="v-fin" features="PR=3P=IND" sentenca="21" />
    <word_480 token="semelhantes" lemma="semelhante, semelhar" pos="adj" features="M=P" sentenca="21" />
    <word_481 token="a" lemma="a" pos="prp" features="-" sentenca="21" />
    <word_482 token="os" lemma="o" pos="art" features="M=P" sentenca="21" />
    <word_483 token="divulgados" lemma="divulgar" pos="v-pcp" features="M=P" sentenca="21" />
    <word_484 token="em" lemma="em" pos="prp" features="-" sentenca="21" />
    <word_485 token="esta" lemma="este" pos="pron-det" features="F=S" sentenca="21" />
    <word_486 token="sexta-feira" lemma="sexta-feira" pos="n" features="F=S" sentenca="21" />
    <word_487 token="." lemma="." pos="." features="-" sentenca="21" />
    <word_488 token="em" lemma="em" pos="prp" features="-" sentenca="22" />
    <word_489 token="a" lemma="o" pos="art" features="F=S" sentenca="22" />
    <word_490 token="pesquisa" lemma="pesquisa" pos="n" features="F=S" sentenca="22" />
    <word_491 token="," lemma="" pos="," features="-" sentenca="22" />
    <word_492 token="divulgada" lemma="divulgar" pos="v-pcp" features="F=S" sentenca="22" />
    <word_493 token="em" lemma="em" pos="prp" features="-" sentenca="22" />
    <word_494 token="o" lemma="o" pos="art" features="M=S" sentenca="22" />
    <word_495 token="último" lemma="último" pos="adj" features="M=S" sentenca="22" />
    <word_496 token="dia" lemma="dia" pos="n" features="M=S" sentenca="22" />
    <word_497 token="19" lemma="" pos="num" features="M=P" sentenca="22" />
    <word_498 token="por" lemma="por" pos="prp" features="-" sentenca="22" />
    <word_499 token="a" lemma="o" pos="art" features="F=S" sentenca="22" />
    <word_500 token="Folha" lemma="Folha" pos="prop" features="-" sentenca="22" />
    <word_501 token="," lemma="" pos="," features="-" sentenca="22" />
    <word_502 token="Lula" lemma="Lula" pos="prop" features="-" sentenca="22" />
    <word_503 token="aparece" lemma="aparecer" pos="v-fin" features="PR=3S=IND" sentenca="22" />
    <word_504 token="com" lemma="com" pos="prp" features="-" sentenca="22" />
    <word_505 token="44" lemma="" pos="num" features="M=P" sentenca="22" />
    <word_506 token="%" lemma="" pos="n" features="M=P" sentenca="22" />
    <word_507 token="de" lemma="de" pos="prp" features="-" sentenca="22" />
    <word_508 token="as" lemma="o" pos="art" features="F=P" sentenca="22" />
    <word_509 token="intenções" lemma="intenção" pos="n" features="F=P" sentenca="22" />
    <word_510 token="de" lemma="de" pos="prp" features="-" sentenca="22" />
    <word_511 token="voto" lemma="voto" pos="n" features="M=S" sentenca="22" />
    <word_512 token="e" lemma="e" pos="conj-c" features="-" sentenca="22" />
    <word_513 token="Alckmin" lemma="" pos="prop" features="M=S" sentenca="22" />
    <word_514 token="," lemma="" pos="," features="-" sentenca="22" />
    <word_515 token="com" lemma="com" pos="prp" features="-" sentenca="22" />
    <word_516 token="28" lemma="" pos="num" features="M=P" sentenca="22" />
    <word_517 token="%" lemma="" pos="n" features="M=P" sentenca="22" />
    <word_518 token="." lemma="." pos="." features="-" sentenca="22" />
    <word_519 token="A" lemma="o" pos="art" features="F=S" sentenca="23" />
    <word_520 token="candidata" lemma="candidato" pos="n" features="F=S" sentenca="23" />
    <word_521 token="de" lemma="de" pos="prp" features="-" sentenca="23" />
    <word_522 token="o" lemma="o" pos="art" features="M=S" sentenca="23" />
    <word_523 token="PSOL" lemma="" pos="prop" features="M=S" sentenca="23" />
    <word_524 token="a" lemma="a" pos="prp" features="-" sentenca="23" />
    <word_525 token="a" lemma="o" pos="art" features="F=S" sentenca="23" />
    <word_526 token="Presidência" lemma="presidência" pos="n" features="F=S" sentenca="23" />
    <word_527 token="vem" lemma="vir" pos="v-fin" features="PR=3S=IND" sentenca="23" />
    <word_528 token="em" lemma="em" pos="prp" features="-" sentenca="23" />
    <word_529 token="terceiro" lemma="" pos="adj" features="M=S" sentenca="23" />
    <word_530 token="," lemma="" pos="," features="-" sentenca="23" />
    <word_531 token="com" lemma="com" pos="prp" features="-" sentenca="23" />
    <word_532 token="10" lemma="" pos="num" features="M=P" sentenca="23" />
    <word_533 token="%" lemma="" pos="n" features="M=P" sentenca="23" />
    <word_534 token="." lemma="." pos="." features="-" sentenca="23" />
  </Tokens>
  <Cadeias>
    <Cadeia_0>
      <sn id="0" tokens="1...2" nucleo="eleição" sintagma="a eleição" Categoria="OUTRO" sentenca="1">
        <word_1 token="a" lemma="o" pos="art" features="F=S" />
        <word_2 token="eleição" lemma="eleição" pos="n" features="F=S" />
      </sn>
      <sn id="4" tokens="12...13" nucleo="reeleição" sintagma="a reeleição" Categoria="OUTRO" sentenca="1">
        <word_12 token="a" lemma="o" pos="art" features="F=S" />
        <word_13 token="reeleição" lemma="eleição" pos="n" features="F=S" />
      </sn>
    </Cadeia_0>
    <Cadeia_1>
      <sn id="1" tokens="6...14" nucleo="presidente" sintagma="o presidente Luiz Inácio Lula de a Silva , candidato a a reeleição" Categoria="PESSOA" sentenca="1">
        <word_6 token="o" lemma="o" pos="art" features="M=S" />
        <word_7 token="presidente" lemma="presidente" pos="n" features="M=S" />
        <word_8 token="Luiz_Inácio_Lula_da_Silva" lemma="" pos="prop" features="M=S" />
        <word_9 token="," lemma="" pos="," features="-" />
        <word_10 token="candidato" lemma="candidato" pos="n" features="M=S" />
        <word_11 token="a" lemma="a" pos="prp" features="-" />
        <word_12 token="a" lemma="o" pos="art" features="F=S" />
        <word_13 token="reeleição" lemma="eleição" pos="n" features="F=S" />
        <word_14 token="," lemma="" pos="," features="-" />
      </sn>
      <sn id="16" tokens="47...48" nucleo="Presidência" sintagma="a Presidência" Categoria="OUTRO" sentenca="2">
        <word_47 token="a" lemma="o" pos="art" features="F=S" />
        <word_48 token="Presidência" lemma="presidência" pos="n" features="F=S" />
      </sn>
      <sn id="71" tokens="248...249" nucleo="presidente" sintagma="o presidente" Categoria="PESSOA" sentenca="10">
        <word_248 token="o" lemma="o" pos="art" features="M=S" />
        <word_249 token="presidente" lemma="presidente" pos="n" features="M=S" />
      </sn>
      <sn id="84" tokens="300...301" nucleo="presidente" sintagma="O presidente" Categoria="PESSOA" sentenca="13">
        <word_300 token="O" lemma="o" pos="art" features="M=S" />
        <word_301 token="presidente" lemma="presidente" pos="n" features="M=S" />
      </sn>
      <sn id="150" tokens="525...526" nucleo="Presidência" sintagma="a Presidência" Categoria="OUTRO" sentenca="23">
        <word_525 token="a" lemma="o" pos="art" features="F=S" />
        <word_526 token="Presidência" lemma="presidência" pos="n" features="F=S" />
      </sn>
    </Cadeia_1>
    <Cadeia_10>
      <sn id="14" tokens="43...52" nucleo="Heloísa_Helena" sintagma="Heloísa Helena , candidata a a Presidência por o PSOL" Categoria="PESSOA" sentenca="2">
        <word_43 token="Heloísa_Helena" lemma="" pos="prop" features="F=S" />
        <word_44 token="," lemma="" pos="," features="-" />
        <word_45 token="candidata" lemma="candidato" pos="n" features="F=S" />
        <word_46 token="a" lemma="a" pos="prp" features="-" />
        <word_47 token="a" lemma="o" pos="art" features="F=S" />
        <word_48 token="Presidência" lemma="presidência" pos="n" features="F=S" />
        <word_49 token="por" lemma="por" pos="prp" features="-" />
        <word_50 token="o" lemma="o" pos="art" features="M=S" />
        <word_51 token="PSOL" lemma="" pos="prop" features="M=S" />
        <word_52 token="," lemma="" pos="," features="-" />
      </sn>
      <sn id="61" tokens="214...214" nucleo="Heloísa" sintagma="Heloísa" Categoria="PESSOA" sentenca="8">
        <word_214 token="Heloísa" lemma="" pos="prop" features="F=S" />
      </sn>
      <sn id="80" tokens="284...284" nucleo="Heloísa_Helena" sintagma="Heloísa Helena" Categoria="PESSOA" sentenca="12">
        <word_284 token="Heloísa_Helena" lemma="" pos="prop" features="M=S" />
      </sn>
      <sn id="88" tokens="314...314" nucleo="Heloísa" sintagma="Heloísa" Categoria="PESSOA" sentenca="13">
        <word_314 token="Heloísa" lemma="" pos="prop" features="M=S" />
      </sn>
      <sn id="91" tokens="324...324" nucleo="Heloísa" sintagma="Heloísa" Categoria="PESSOA" sentenca="14">
        <word_324 token="Heloísa" lemma="" pos="prop" features="F=S" />
      </sn>
      <sn id="113" tokens="398...398" nucleo="Heloísa" sintagma="Heloísa" Categoria="PESSOA" sentenca="18">
        <word_398 token="Heloísa" lemma="" pos="prop" features="F=S" />
      </sn>
      <sn id="130" tokens="453...453" nucleo="Heloísa" sintagma="Heloísa" Categoria="PESSOA" sentenca="20">
        <word_453 token="Heloísa" lemma="" pos="prop" features="F=S" />
      </sn>
      <sn id="148" tokens="519...526" nucleo="candidata" sintagma="A candidata de o PSOL a a Presidência" Categoria="OUTRO" sentenca="23">
        <word_519 token="A" lemma="o" pos="art" features="F=S" />
        <word_520 token="candidata" lemma="candidato" pos="n" features="F=S" />
        <word_521 token="de" lemma="de" pos="prp" features="-" />
        <word_522 token="o" lemma="o" pos="art" features="M=S" />
        <word_523 token="PSOL" lemma="" pos="prop" features="M=S" />
        <word_524 token="a" lemma="a" pos="prp" features="-" />
        <word_525 token="a" lemma="o" pos="art" features="F=S" />
        <word_526 token="Presidência" lemma="presidência" pos="n" features="F=S" />
      </sn>
    </Cadeia_10>
    <Cadeia_11>
      <sn id="17" tokens="50...51" nucleo="PSOL" sintagma="o PSOL" Categoria="OUTRO" sentenca="2">
        <word_50 token="o" lemma="o" pos="art" features="M=S" />
        <word_51 token="PSOL" lemma="" pos="prop" features="M=S" />
      </sn>
      <sn id="149" tokens="522...523" nucleo="PSOL" sintagma="o PSOL" Categoria="OUTRO" sentenca="23">
        <word_522 token="o" lemma="o" pos="art" features="M=S" />
        <word_523 token="PSOL" lemma="" pos="prop" features="M=S" />
      </sn>
    </Cadeia_11>
    <Cadeia_12>
      <sn id="21" tokens="68...68" nucleo="Cristovam_Buarque" sintagma="Cristovam Buarque" Categoria="OUTRO" sentenca="2">
        <word_68 token="Cristovam_Buarque" lemma="" pos="prop" features="M=S" />
      </sn>
      <sn id="22" tokens="70...70" nucleo="PDT" sintagma="PDT" Categoria="OUTRO" sentenca="2">
        <word_70 token="PDT" lemma="" pos="prop" features="M=S" />
      </sn>
    </Cadeia_12>
    <Cadeia_13>
      <sn id="23" tokens="73...73" nucleo="Luciano_Bivar" sintagma="Luciano Bivar" Categoria="PESSOA" sentenca="2">
        <word_73 token="Luciano_Bivar" lemma="" pos="prop" features="M=S" />
      </sn>
      <sn id="24" tokens="75...75" nucleo="PSL" sintagma="PSL" Categoria="OUTRO" sentenca="2">
        <word_75 token="PSL" lemma="" pos="prop" features="M=S" />
      </sn>
    </Cadeia_13>
    <Cadeia_18>
      <sn id="35" tokens="114...114" nucleo="Lula" sintagma="Lula" Categoria="PESSOA" sentenca="4">
        <word_114 token="Lula" lemma="Lula" pos="prop" features="-" />
      </sn>
      <sn id="55" tokens="196...196" nucleo="Lula" sintagma="Lula" Categoria="PESSOA" sentenca="7">
        <word_196 token="Lula" lemma="Lula" pos="prop" features="-" />
      </sn>
      <sn id="66" tokens="236...236" nucleo="Lula" sintagma="Lula" Categoria="PESSOA" sentenca="9">
        <word_236 token="Lula" lemma="Lula" pos="prop" features="-" />
      </sn>
      <sn id="76" tokens="267...267" nucleo="Lula" sintagma="Lula" Categoria="PESSOA" sentenca="11">
        <word_267 token="Lula" lemma="Lula" pos="prop" features="-" />
      </sn>
      <sn id="82" tokens="289...289" nucleo="Lula" sintagma="Lula" Categoria="PESSOA" sentenca="12">
        <word_289 token="Lula" lemma="Lula" pos="prop" features="-" />
      </sn>
      <sn id="90" tokens="319...319" nucleo="Lula" sintagma="Lula" Categoria="PESSOA" sentenca="14">
        <word_319 token="Lula" lemma="Lula" pos="prop" features="-" />
      </sn>
      <sn id="107" tokens="377...377" nucleo="Lula" sintagma="Lula" Categoria="PESSOA" sentenca="17">
        <word_377 token="Lula" lemma="Lula" pos="prop" features="-" />
      </sn>
      <sn id="122" tokens="428...428" nucleo="Lula" sintagma="Lula" Categoria="PESSOA" sentenca="19">
        <word_428 token="Lula" lemma="Lula" pos="prop" features="-" />
      </sn>
      <sn id="129" tokens="451...451" nucleo="Lula" sintagma="Lula" Categoria="PESSOA" sentenca="20">
        <word_451 token="Lula" lemma="Lula" pos="prop" features="-" />
      </sn>
      <sn id="142" tokens="502...502" nucleo="Lula" sintagma="Lula" Categoria="PESSOA" sentenca="22">
        <word_502 token="Lula" lemma="Lula" pos="prop" features="-" />
      </sn>
    </Cadeia_18>
    <Cadeia_2>
      <sn id="3" tokens="10...10" nucleo="candidato" sintagma="candidato" Categoria="OUTRO" sentenca="1">
        <word_10 token="candidato" lemma="candidato" pos="n" features="M=S" />
      </sn>
      <sn id="15" tokens="45...45" nucleo="candidata" sintagma="candidata" Categoria="OUTRO" sentenca="2">
        <word_45 token="candidata" lemma="candidato" pos="n" features="F=S" />
      </sn>
      <sn id="44" tokens="152...153" nucleo="candidatos" sintagma="os candidatos" Categoria="OUTRO" sentenca="5">
        <word_152 token="os" lemma="o" pos="art" features="M=P" />
        <word_153 token="candidatos" lemma="candidato" pos="n" features="M=P" />
      </sn>
    </Cadeia_2>
    <Cadeia_21>
      <sn id="38" tokens="122...124" nucleo="turno" sintagma="o primeiro turno" Categoria="OUTROS SERES/MITLG" sentenca="4">
        <word_122 token="o" lemma="o" pos="art" features="M=S" />
        <word_123 token="primeiro" lemma="primeiro" pos="adj" features="M=S" />
        <word_124 token="turno" lemma="turno" pos="n" features="M=S" />
      </sn>
      <sn id="79" tokens="282...282" nucleo="turno" sintagma="turno" Categoria="OUTROS SERES/MITLG" sentenca="12">
        <word_282 token="turno" lemma="turno" pos="n" features="M=S" />
      </sn>
      <sn id="117" tokens="414...414" nucleo="turno" sintagma="turno" Categoria="OUTROS SERES/MITLG" sentenca="19">
        <word_414 token="turno" lemma="turno" pos="n" features="M=S" />
      </sn>
    </Cadeia_21>
    <Cadeia_22>
      <sn id="39" tokens="130...134" nucleo="comparação" sintagma="uma comparação entre a pesquisa" Categoria="OUTRO" sentenca="5">
        <word_130 token="uma" lemma="um" pos="art" features="F=S" />
        <word_131 token="comparação" lemma="comparação, comparar" pos="n" features="F=S" />
        <word_132 token="entre" lemma="entre" pos="prp" features="-" />
        <word_133 token="a" lemma="o" pos="art" features="F=S" />
        <word_134 token="pesquisa" lemma="pesquisa" pos="n" features="F=S" />
      </sn>
      <sn id="54" tokens="193...194" nucleo="este" sintagma="este cenário" Categoria="OUTRO" sentenca="7">
        <word_193 token="este" lemma="este" pos="pron-det" features="M=S" />
        <word_194 token="cenário" lemma="cenário" pos="n" features="M=S" />
      </sn>
      <sn id="83" tokens="295...296" nucleo="pesquisa" sintagma="a pesquisa" Categoria="OUTRO" sentenca="12">
        <word_295 token="a" lemma="o" pos="art" features="F=S" />
        <word_296 token="pesquisa" lemma="pesquisa" pos="n" features="F=S" />
      </sn>
      <sn id="93" tokens="328...329" nucleo="pesquisa" sintagma="A pesquisa" Categoria="OUTRO" sentenca="15">
        <word_328 token="A" lemma="o" pos="art" features="F=S" />
        <word_329 token="pesquisa" lemma="pesquisa" pos="n" features="F=S" />
      </sn>
      <sn id="103" tokens="366...367" nucleo="comparação" sintagma="a comparação" Categoria="OUTRO" sentenca="17">
        <word_366 token="a" lemma="o" pos="art" features="F=S" />
        <word_367 token="comparação" lemma="comparação, comparar" pos="n" features="F=S" />
      </sn>
      <sn id="104" tokens="369...370" nucleo="pesquisa" sintagma="a pesquisa" Categoria="OUTRO" sentenca="17">
        <word_369 token="a" lemma="o" pos="art" features="F=S" />
        <word_370 token="pesquisa" lemma="pesquisa" pos="n" features="F=S" />
      </sn>
      <sn id="105" tokens="371...371" nucleo="Ibope" sintagma="Ibope" Categoria="OUTRO" sentenca="17">
        <word_371 token="Ibope" lemma="" pos="prop" features="F=S" />
      </sn>
      <sn id="118" tokens="417...418" nucleo="comparação" sintagma="a comparação" Categoria="OUTRO" sentenca="19">
        <word_417 token="a" lemma="o" pos="art" features="F=S" />
        <word_418 token="comparação" lemma="comparação, comparar" pos="n" features="F=S" />
      </sn>
      <sn id="119" tokens="420...421" nucleo="pesquisa" sintagma="a pesquisa" Categoria="OUTRO" sentenca="19">
        <word_420 token="a" lemma="o" pos="art" features="F=S" />
        <word_421 token="pesquisa" lemma="pesquisa" pos="n" features="F=S" />
      </sn>
      <sn id="120" tokens="422...422" nucleo="Ibope" sintagma="Ibope" Categoria="OUTRO" sentenca="19">
        <word_422 token="Ibope" lemma="" pos="prop" features="F=S" />
      </sn>
      <sn id="132" tokens="462...463" nucleo="Ibope" sintagma="o Ibope" Categoria="OUTRO" sentenca="20">
        <word_462 token="o" lemma="o" pos="art" features="M=S" />
        <word_463 token="Ibope" lemma="" pos="prop" features="M=S" />
      </sn>
      <sn id="139" tokens="489...490" nucleo="pesquisa" sintagma="a pesquisa" Categoria="OUTRO" sentenca="22">
        <word_489 token="a" lemma="o" pos="art" features="F=S" />
        <word_490 token="pesquisa" lemma="pesquisa" pos="n" features="F=S" />
      </sn>
    </Cadeia_22>
    <Cadeia_25>
      <sn id="43" tokens="148...150" nucleo="lista" sintagma="a lista oficial" Categoria="OUTRO" sentenca="5">
        <word_148 token="a" lemma="o" pos="art" features="F=S" />
        <word_149 token="lista" lemma="lista" pos="n" features="F=S" />
        <word_150 token="oficial" lemma="oficial" pos="adj" features="F=S" />
      </sn>
      <sn id="141" tokens="499...500" nucleo="Folha" sintagma="a Folha" Categoria="OUTRO" sentenca="22">
        <word_499 token="a" lemma="o" pos="art" features="F=S" />
        <word_500 token="Folha" lemma="Folha" pos="prop" features="-" />
      </sn>
    </Cadeia_25>
    <Cadeia_26>
      <sn id="45" tokens="155...156" nucleo="TSE" sintagma="o TSE" Categoria="OUTRO" sentenca="5">
        <word_155 token="o" lemma="o" pos="art" features="M=S" />
        <word_156 token="TSE" lemma="" pos="prop" features="M=S" />
      </sn>
      <sn id="46" tokens="158...158" nucleo="Tribunal_Superior_Eleitoral" sintagma="Tribunal Superior Eleitoral" Categoria="OUTRO" sentenca="5">
        <word_158 token="Tribunal_Superior_Eleitoral" lemma="" pos="prop" features="M=S" />
      </sn>
    </Cadeia_26>
    <Cadeia_3>
      <sn id="5" tokens="19...20" nucleo="intenções" sintagma="as intenções" Categoria="OUTRO" sentenca="1">
        <word_19 token="as" lemma="o" pos="art" features="F=P" />
        <word_20 token="intenções" lemma="intenção" pos="n" features="F=P" />
      </sn>
      <sn id="19" tokens="61...62" nucleo="intenções" sintagma="as intenções" Categoria="OUTRO" sentenca="2">
        <word_61 token="as" lemma="o" pos="art" features="F=P" />
        <word_62 token="intenções" lemma="intenção" pos="n" features="F=P" />
      </sn>
      <sn id="32" tokens="103...104" nucleo="intenções" sintagma="as intenções" Categoria="OUTRO" sentenca="3">
        <word_103 token="as" lemma="o" pos="art" features="F=P" />
        <word_104 token="intenções" lemma="intenção" pos="n" features="F=P" />
      </sn>
      <sn id="72" tokens="254...255" nucleo="intenções" sintagma="as intenções" Categoria="OUTRO" sentenca="10">
        <word_254 token="as" lemma="o" pos="art" features="F=P" />
        <word_255 token="intenções" lemma="intenção" pos="n" features="F=P" />
      </sn>
      <sn id="85" tokens="306...307" nucleo="intenções" sintagma="as intenções" Categoria="OUTRO" sentenca="13">
        <word_306 token="as" lemma="o" pos="art" features="F=P" />
        <word_307 token="intenções" lemma="intenção" pos="n" features="F=P" />
      </sn>
      <sn id="144" tokens="508...509" nucleo="intenções" sintagma="as intenções" Categoria="OUTRO" sentenca="22">
        <word_508 token="as" lemma="o" pos="art" features="F=P" />
        <word_509 token="intenções" lemma="intenção" pos="n" features="F=P" />
      </sn>
    </Cadeia_3>
    <Cadeia_30>
      <sn id="49" tokens="170...179" nucleo="variação" sintagma="uma variação em a lista espontânea  quando os entrevistados" Categoria="OUTRO" sentenca="6">
        <word_170 token="uma" lemma="um" pos="art" features="F=S" />
        <word_171 token="variação" lemma="variação, variar" pos="n" features="F=S" />
        <word_172 token="em" lemma="em" pos="prp" features="-" />
        <word_173 token="a" lemma="o" pos="art" features="F=S" />
        <word_174 token="lista" lemma="lista" pos="n" features="F=S" />
        <word_175 token="espontânea" lemma="espontâneo" pos="adj" features="F=S" />
        <word_176 token="(" lemma="(" pos="(" features="-" />
        <word_177 token="quando" lemma="quando" pos="adv" features="-" />
        <word_178 token="os" lemma="o" pos="art" features="M=P" />
        <word_179 token="entrevistados" lemma="entrevistar" pos="v-pcp" features="M=P" />
      </sn>
      <sn id="50" tokens="173...175" nucleo="lista" sintagma="a lista espontânea" Categoria="OUTRO" sentenca="6">
        <word_173 token="a" lemma="o" pos="art" features="F=S" />
        <word_174 token="lista" lemma="lista" pos="n" features="F=S" />
        <word_175 token="espontânea" lemma="espontâneo" pos="adj" features="F=S" />
      </sn>
      <sn id="51" tokens="177...189" nucleo="quem" sintagma=" quando os entrevistados dizem em quem pretendem votar sem um cartão com nomes " Categoria="OUTRO" sentenca="6">
        <word_177 token="quando" lemma="quando" pos="adv" features="-" />
        <word_178 token="os" lemma="o" pos="art" features="M=P" />
        <word_179 token="entrevistados" lemma="entrevistar" pos="v-pcp" features="M=P" />
        <word_180 token="dizem" lemma="dizer" pos="v-fin" features="PR=3P=IND" />
        <word_181 token="em" lemma="em" pos="prp" features="-" />
        <word_182 token="quem" lemma="quem" pos="pron-indp" features="M/F=S" />
        <word_183 token="pretendem" lemma="pretender" pos="v-fin" features="PR=3P=IND" />
        <word_184 token="votar" lemma="votar" pos="v-inf" features="-" />
        <word_185 token="sem" lemma="sem" pos="prp" features="-" />
        <word_186 token="um" lemma="um" pos="art" features="M=S" />
        <word_187 token="cartão" lemma="cartão" pos="n" features="M=S" />
        <word_188 token="com" lemma="com" pos="prp" features="-" />
        <word_189 token="nomes" lemma="nome" pos="n" features="M=P" />
      </sn>
    </Cadeia_30>
    <Cadeia_34>
      <sn id="65" tokens="231...234" nucleo="turno" sintagma="um possível segundo turno" Categoria="ABSTRAÇÃO" sentenca="9">
        <word_231 token="um" lemma="um" pos="art" features="M=S" />
        <word_232 token="possível" lemma="possível" pos="adj" features="M=S" />
        <word_233 token="segundo" lemma="" pos="adj" features="M=S" />
        <word_234 token="turno" lemma="turno" pos="n" features="M=S" />
      </sn>
      <sn id="128" tokens="447...457" nucleo="disputa" sintagma="Uma possível disputa entre Lula e Heloísa em um segundo turno" Categoria="ABSTRAÇÃO" sentenca="20">
        <word_447 token="Uma" lemma="um" pos="art" features="F=S" />
        <word_448 token="possível" lemma="possível" pos="adj" features="F=S" />
        <word_449 token="disputa" lemma="disputa" pos="n" features="F=S" />
        <word_450 token="entre" lemma="entre" pos="prp" features="-" />
        <word_451 token="Lula" lemma="Lula" pos="prop" features="-" />
        <word_452 token="e" lemma="e" pos="conj-c" features="-" />
        <word_453 token="Heloísa" lemma="" pos="prop" features="F=S" />
        <word_454 token="em" lemma="em" pos="prp" features="-" />
        <word_455 token="um" lemma="um" pos="art" features="M=S" />
        <word_456 token="segundo" lemma="" pos="adj" features="M=S" />
        <word_457 token="turno" lemma="turno" pos="n" features="M=S" />
      </sn>
      <sn id="131" tokens="455...457" nucleo="turno" sintagma="um segundo turno" Categoria="ABSTRAÇÃO" sentenca="20">
        <word_455 token="um" lemma="um" pos="art" features="M=S" />
        <word_456 token="segundo" lemma="" pos="adj" features="M=S" />
        <word_457 token="turno" lemma="turno" pos="n" features="M=S" />
      </sn>
    </Cadeia_34>
    <Cadeia_36>
      <sn id="70" tokens="246...246" nucleo="junho" sintagma="junho" Categoria="ABSTRAÇÃO" sentenca="10">
        <word_246 token="junho" lemma="junho" pos="n" features="M=S" />
      </sn>
      <sn id="89" tokens="317...317" nucleo="junho" sintagma="junho" Categoria="ABSTRAÇÃO" sentenca="14">
        <word_317 token="junho" lemma="junho" pos="n" features="M=S" />
      </sn>
    </Cadeia_36>
    <Cadeia_38>
      <sn id="95" tokens="334...335" nucleo="dias" sintagma="os dias" Categoria="PESSOA" sentenca="15">
        <word_334 token="os" lemma="o" pos="art" features="M=P" />
        <word_335 token="dias" lemma="dia" pos="n" features="M=P" />
      </sn>
      <sn id="106" tokens="374...375" nucleo="dias" sintagma="nove dias" Categoria="PESSOA" sentenca="17">
        <word_374 token="nove" lemma="nove" pos="num" features="M=P" />
        <word_375 token="dias" lemma="dia" pos="n" features="M=P" />
      </sn>
      <sn id="121" tokens="424...426" nucleo="dia" sintagma="o dia 25" Categoria="OUTRO/UNID" sentenca="19">
        <word_424 token="o" lemma="o" pos="art" features="M=S" />
        <word_425 token="dia" lemma="dia" pos="n" features="M=S" />
        <word_426 token="25" lemma="" pos="num" features="M=P" />
      </sn>
      <sn id="134" tokens="468...470" nucleo="dia" sintagma="o dia 25" Categoria="OUTRO/UNID" sentenca="20">
        <word_468 token="o" lemma="o" pos="art" features="M=S" />
        <word_469 token="dia" lemma="dia" pos="n" features="M=S" />
        <word_470 token="25" lemma="" pos="num" features="M=P" />
      </sn>
    </Cadeia_38>
    <Cadeia_4>
      <sn id="6" tokens="22...22" nucleo="voto" sintagma="voto" Categoria="OUTRO" sentenca="1">
        <word_22 token="voto" lemma="voto" pos="n" features="M=S" />
      </sn>
      <sn id="20" tokens="64...64" nucleo="voto" sintagma="voto" Categoria="OUTRO" sentenca="2">
        <word_64 token="voto" lemma="voto" pos="n" features="M=S" />
      </sn>
      <sn id="33" tokens="106...106" nucleo="voto" sintagma="voto" Categoria="OUTRO" sentenca="3">
        <word_106 token="voto" lemma="voto" pos="n" features="M=S" />
      </sn>
      <sn id="73" tokens="257...257" nucleo="voto" sintagma="voto" Categoria="OUTRO" sentenca="10">
        <word_257 token="voto" lemma="voto" pos="n" features="M=S" />
      </sn>
      <sn id="86" tokens="309...309" nucleo="voto" sintagma="voto" Categoria="OUTRO" sentenca="13">
        <word_309 token="voto" lemma="voto" pos="n" features="M=S" />
      </sn>
      <sn id="145" tokens="511...511" nucleo="voto" sintagma="voto" Categoria="OUTRO" sentenca="22">
        <word_511 token="voto" lemma="voto" pos="n" features="M=S" />
      </sn>
    </Cadeia_4>
    <Cadeia_45>
      <sn id="101" tokens="354...357" nucleo="pontos" sintagma="dois pontos percentuais" Categoria="ABSTRAÇÃO" sentenca="16">
        <word_354 token="de" lemma="de" pos="prp" features="-" />
        <word_355 token="dois" lemma="dois" pos="num" features="M=P" />
        <word_356 token="pontos" lemma="ponto" pos="n" features="M=P" />
        <word_357 token="percentuais" lemma="percentual" pos="adj" features="M=P" />
      </sn>
      <sn id="110" tokens="386...395" nucleo="pontos" sintagma="dois pontos percentuais , de 27 % para 25 %" Categoria="ABSTRAÇÃO" sentenca="17">
        <word_386 token="dois" lemma="dois" pos="num" features="M=P" />
        <word_387 token="pontos" lemma="ponto" pos="n" features="M=P" />
        <word_388 token="percentuais" lemma="percentual" pos="adj" features="M=P" />
        <word_389 token="," lemma="" pos="," features="-" />
        <word_390 token="de" lemma="de" pos="prp" features="-" />
        <word_391 token="27" lemma="" pos="num" features="M=P" />
        <word_392 token="%" lemma="" pos="n" features="M=P" />
        <word_393 token="para" lemma="para" pos="prp" features="-" />
        <word_394 token="25" lemma="" pos="num" features="M=P" />
        <word_395 token="%" lemma="" pos="n" features="M=P" />
      </sn>
      <sn id="114" tokens="400...408" nucleo="pontos" sintagma="três pontos , de 8 % para 11 %" Categoria="ABSTRAÇÃO" sentenca="18">
        <word_400 token="três" lemma="três" pos="num" features="M=P" />
        <word_401 token="pontos" lemma="ponto" pos="n" features="M=P" />
        <word_402 token="," lemma="" pos="," features="-" />
        <word_403 token="de" lemma="de" pos="prp" features="-" />
        <word_404 token="8" lemma="" pos="num" features="M=P" />
        <word_405 token="%" lemma="" pos="n" features="M=P" />
        <word_406 token="para" lemma="para" pos="prp" features="-" />
        <word_407 token="11" lemma="" pos="num" features="M=P" />
        <word_408 token="%" lemma="" pos="n" features="M=P" />
      </sn>
    </Cadeia_45>
    <Cadeia_5>
      <sn id="8" tokens="28...29" nucleo="tucano" sintagma="o tucano" Categoria="ORGANIZAÇÃO|LOCAL" sentenca="1">
        <word_28 token="o" lemma="o" pos="art" features="M=S" />
        <word_29 token="tucano" lemma="tucano" pos="n" features="M=S" />
      </sn>
      <sn id="75" tokens="262...263" nucleo="tucano" sintagma="o tucano" Categoria="ORGANIZAÇÃO|LOCAL" sentenca="10">
        <word_262 token="o" lemma="o" pos="art" features="M=S" />
        <word_263 token="tucano" lemma="tucano" pos="n" features="M=S" />
      </sn>
    </Cadeia_5>
    <Cadeia_50>
      <sn id="135" tokens="472...478" nucleo="números" sintagma="Os números de a última pesquisa Datafolha" Categoria="OUTRO" sentenca="21">
        <word_472 token="Os" lemma="o" pos="art" features="M=P" />
        <word_473 token="números" lemma="número" pos="n" features="M=P" />
        <word_474 token="de" lemma="de" pos="prp" features="-" />
        <word_475 token="a" lemma="o" pos="art" features="F=S" />
        <word_476 token="última" lemma="último" pos="adj" features="F=S" />
        <word_477 token="pesquisa" lemma="pesquisa" pos="n" features="F=S" />
        <word_478 token="Datafolha" lemma="" pos="prop" features="F=S" />
      </sn>
      <sn id="136" tokens="475...477" nucleo="pesquisa" sintagma="a última pesquisa" Categoria="OUTRO" sentenca="21">
        <word_475 token="a" lemma="o" pos="art" features="F=S" />
        <word_476 token="última" lemma="último" pos="adj" features="F=S" />
        <word_477 token="pesquisa" lemma="pesquisa" pos="n" features="F=S" />
      </sn>
      <sn id="137" tokens="478...478" nucleo="Datafolha" sintagma="Datafolha" Categoria="OUTRO" sentenca="21">
        <word_478 token="Datafolha" lemma="" pos="prop" features="F=S" />
      </sn>
    </Cadeia_50>
    <Cadeia_51>
      <sn id="36" tokens="116...119" nucleo="eleições" sintagma="as eleições de outubro" Categoria="OUTRO" sentenca="4">
        <word_116 token="as" lemma="o" pos="art" features="F=P" />
        <word_117 token="eleições" lemma="eleição" pos="n" features="F=P" />
        <word_118 token="de" lemma="de" pos="prp" features="-" />
        <word_119 token="outubro" lemma="outubro" pos="n" features="M=S" />
      </sn>
      <sn id="37" tokens="119...119" nucleo="outubro" sintagma="outubro" Categoria="OUTRO" sentenca="4">
        <word_119 token="outubro" lemma="outubro" pos="n" features="M=S" />
      </sn>
    </Cadeia_51>
    <Cadeia_52>
      <sn id="99" tokens="349...352" nucleo="margem" sintagma="A margem de erro" Categoria="OUTRO" sentenca="16">
        <word_349 token="A" lemma="o" pos="art" features="F=S" />
        <word_350 token="margem" lemma="margem" pos="n" features="F=S" />
        <word_351 token="de" lemma="de" pos="prp" features="-" />
        <word_352 token="erro" lemma="erro" pos="n" features="M=S" />
      </sn>
      <sn id="100" tokens="352...352" nucleo="erro" sintagma="erro" Categoria="OUTRO" sentenca="16">
        <word_352 token="erro" lemma="erro" pos="n" features="M=S" />
      </sn>
    </Cadeia_52>
    <Cadeia_53>
      <sn id="13" tokens="40...41" nucleo="esta" sintagma="esta sexta-feira" Categoria="OUTRO" sentenca="1">
        <word_40 token="esta" lemma="este" pos="pron-det" features="F=S" />
        <word_41 token="sexta-feira" lemma="sexta-feira" pos="n" features="F=S" />
      </sn>
      <sn id="138" tokens="485...486" nucleo="esta" sintagma="esta sexta-feira" Categoria="OUTRO" sentenca="21">
        <word_485 token="esta" lemma="este" pos="pron-det" features="F=S" />
        <word_486 token="sexta-feira" lemma="sexta-feira" pos="n" features="F=S" />
      </sn>
    </Cadeia_53>
    <Cadeia_54>
      <sn id="27" tokens="83...95" nucleo="José_Maria_Eymael" sintagma="José Maria Eymael , de o PSDC , e Rui Pimenta , de o PCO" Categoria="OUTRO" sentenca="3">
        <word_83 token="José_Maria_Eymael" lemma="" pos="prop" features="M=S" />
        <word_84 token="," lemma="" pos="," features="-" />
        <word_85 token="de" lemma="de" pos="prp" features="-" />
        <word_86 token="o" lemma="o" pos="art" features="M=S" />
        <word_87 token="PSDC" lemma="" pos="prop" features="M=S" />
        <word_88 token="," lemma="" pos="," features="-" />
        <word_89 token="e" lemma="e" pos="conj-c" features="-" />
        <word_90 token="Rui_Pimenta" lemma="" pos="prop" features="M=S" />
        <word_91 token="," lemma="" pos="," features="-" />
        <word_92 token="de" lemma="de" pos="prp" features="-" />
        <word_93 token="o" lemma="o" pos="art" features="M=S" />
        <word_94 token="PCO" lemma="" pos="prop" features="M=S" />
        <word_95 token="," lemma="" pos="," features="-" />
      </sn>
      <sn id="30" tokens="93...94" nucleo="PCO" sintagma="o PCO" Categoria="OUTRO" sentenca="3">
        <word_93 token="o" lemma="o" pos="art" features="M=S" />
        <word_94 token="PCO" lemma="" pos="prop" features="M=S" />
      </sn>
    </Cadeia_54>
    <Cadeia_6>
      <sn id="9" tokens="30...30" nucleo="Geraldo_Alckmin" sintagma="Geraldo Alckmin" Categoria="PESSOA" sentenca="1">
        <word_30 token="Geraldo_Alckmin" lemma="" pos="prop" features="M=S" />
      </sn>
      <sn id="58" tokens="205...205" nucleo="Alckmin" sintagma="Alckmin" Categoria="OUTRO" sentenca="7">
        <word_205 token="Alckmin" lemma="" pos="prop" features="M=S" />
      </sn>
      <sn id="69" tokens="243...243" nucleo="Alckmin" sintagma="Alckmin" Categoria="OUTRO" sentenca="9">
        <word_243 token="Alckmin" lemma="" pos="prop" features="M=S" />
      </sn>
      <sn id="78" tokens="276...276" nucleo="Alckmin" sintagma="Alckmin" Categoria="OUTRO" sentenca="11">
        <word_276 token="Alckmin" lemma="" pos="prop" features="M=S" />
      </sn>
      <sn id="109" tokens="384...384" nucleo="Alckmin" sintagma="Alckmin" Categoria="OUTRO" sentenca="17">
        <word_384 token="Alckmin" lemma="" pos="prop" features="F=S" />
      </sn>
      <sn id="125" tokens="438...438" nucleo="Alckmin" sintagma="Alckmin" Categoria="OUTRO" sentenca="19">
        <word_438 token="Alckmin" lemma="" pos="prop" features="M=S" />
      </sn>
      <sn id="146" tokens="513...513" nucleo="Alckmin" sintagma="Alckmin" Categoria="OUTRO" sentenca="22">
        <word_513 token="Alckmin" lemma="" pos="prop" features="M=S" />
      </sn>
    </Cadeia_6>
    <Cadeia_8>
      <sn id="11" tokens="35...36" nucleo="pesquisa" sintagma="a pesquisa" Categoria="OUTRO" sentenca="1">
        <word_35 token="a" lemma="o" pos="art" features="F=S" />
        <word_36 token="pesquisa" lemma="pesquisa" pos="n" features="F=S" />
      </sn>
      <sn id="12" tokens="37...37" nucleo="CNI/Ibope" sintagma="CNI/Ibope" Categoria="OUTRO" sentenca="1">
        <word_37 token="CNI/Ibope" lemma="" pos="prop" features="F=S" />
      </sn>
      <sn id="41" tokens="142...142" nucleo="esta" sintagma="esta" Categoria="OUTRO" sentenca="5">
        <word_142 token="esta" lemma="este" pos="pron-det" features="F=S" />
      </sn>
      <sn id="42" tokens="144...157" nucleo="CNI/Ibope" sintagma="a primeira CNI/Ibope com a lista oficial de os candidatos de o TSE " Categoria="OUTRO" sentenca="5">
        <word_144 token="a" lemma="o" pos="art" features="F=S" />
        <word_145 token="primeira" lemma="" pos="adj" features="F=S" />
        <word_146 token="CNI/Ibope" lemma="" pos="prop" features="M=S" />
        <word_147 token="com" lemma="com" pos="prp" features="-" />
        <word_148 token="a" lemma="o" pos="art" features="F=S" />
        <word_149 token="lista" lemma="lista" pos="n" features="F=S" />
        <word_150 token="oficial" lemma="oficial" pos="adj" features="F=S" />
        <word_151 token="de" lemma="de" pos="prp" features="-" />
        <word_152 token="os" lemma="o" pos="art" features="M=P" />
        <word_153 token="candidatos" lemma="candidato" pos="n" features="M=P" />
        <word_154 token="de" lemma="de" pos="prp" features="-" />
        <word_155 token="o" lemma="o" pos="art" features="M=S" />
        <word_156 token="TSE" lemma="" pos="prop" features="M=S" />
        <word_157 token="(" lemma="(" pos="(" features="-" />
      </sn>
      <sn id="48" tokens="165...168" nucleo="pesquisa" sintagma="A pesquisa de hoje" Categoria="OUTRO" sentenca="6">
        <word_165 token="A" lemma="o" pos="art" features="F=S" />
        <word_166 token="pesquisa" lemma="pesquisa" pos="n" features="F=S" />
        <word_167 token="de" lemma="de" pos="prp" features="-" />
        <word_168 token="hoje" lemma="hoje" pos="adv" features="-" />
      </sn>
      <sn id="64" tokens="227...228" nucleo="CNI/Ibope" sintagma="a CNI/Ibope" Categoria="OUTRO" sentenca="9">
        <word_227 token="a" lemma="o" pos="art" features="F=S" />
        <word_228 token="CNI/Ibope" lemma="" pos="prop" features="F=S" />
      </sn>
    </Cadeia_8>
  </Cadeias>
  <Mencoes_Unicas>
    <sn id="10" tokens="33...33" nucleo="acordo" sintagma="acordo" Categoria="--" sentenca="1">
      <word_33 token="acordo" lemma="acordo" pos="n" features="M=S" />
    </sn>
    <sn id="25" tokens="78...78" nucleo="ambos" sintagma="ambos" Categoria="--" sentenca="2">
      <word_78 token="ambos" lemma="ambos" pos="pron-det" features="M=P" />
    </sn>
    <sn id="34" tokens="110...112" nucleo="votos" sintagma="os votos válidos" Categoria="--" sentenca="4">
      <word_110 token="os" lemma="o" pos="art" features="M=P" />
      <word_111 token="votos" lemma="voto" pos="n" features="M=P" />
      <word_112 token="válidos" lemma="válido" pos="adj" features="M=P" />
    </sn>
    <sn id="47" tokens="161...163" nucleo="sucessão" sintagma="a sucessão presidencial" Categoria="--" sentenca="5">
      <word_161 token="a" lemma="o" pos="art" features="F=S" />
      <word_162 token="sucessão" lemma="sucessão" pos="n" features="F=S" />
      <word_163 token="presidencial" lemma="presidencial" pos="adj" features="F=S" />
    </sn>
    <sn id="52" tokens="186...187" nucleo="cartão" sintagma="um cartão" Categoria="--" sentenca="6">
      <word_186 token="um" lemma="um" pos="art" features="M=S" />
      <word_187 token="cartão" lemma="cartão" pos="n" features="M=S" />
    </sn>
    <sn id="53" tokens="189...189" nucleo="nomes" sintagma="nomes" Categoria="--" sentenca="6">
      <word_189 token="nomes" lemma="nome" pos="n" features="M=P" />
    </sn>
    <sn id="68" tokens="241...241" nucleo="vantagem" sintagma="vantagem" Categoria="--" sentenca="9">
      <word_241 token="vantagem" lemma="vantagem" pos="n" features="F=S" />
    </sn>
    <sn id="81" tokens="286...289" nucleo="vantagem" sintagma="a vantagem de Lula" Categoria="--" sentenca="12">
      <word_286 token="a" lemma="o" pos="art" features="F=S" />
      <word_287 token="vantagem" lemma="vantagem" pos="n" features="F=S" />
      <word_288 token="de" lemma="de" pos="prp" features="-" />
      <word_289 token="Lula" lemma="Lula" pos="prop" features="-" />
    </sn>
    <sn id="96" tokens="340...340" nucleo="julho" sintagma="julho" Categoria="--" sentenca="15">
      <word_340 token="julho" lemma="julho" pos="n" features="M=S" />
    </sn>
    <sn id="98" tokens="346...347" nucleo="país" sintagma="o país" Categoria="--" sentenca="15">
      <word_346 token="o" lemma="o" pos="art" features="M=S" />
      <word_347 token="país" lemma="país" pos="n" features="M=S" />
    </sn>
    <sn id="102" tokens="363...363" nucleo="menos" sintagma="menos" Categoria="--" sentenca="16">
      <word_363 token="menos" lemma="menos" pos="pron-det" features="M=P" />
    </sn>
    <sn id="133" tokens="465...466" nucleo="esse" sintagma="esse levantamento" Categoria="--" sentenca="20">
      <word_465 token="esse" lemma="esse" pos="pron-det" features="M=S" />
      <word_466 token="levantamento" lemma="levantar" pos="n" features="M=S" />
    </sn>
    <sn id="140" tokens="494...497" nucleo="dia" sintagma="o último dia 19" Categoria="--" sentenca="22">
      <word_494 token="o" lemma="o" pos="art" features="M=S" />
      <word_495 token="último" lemma="último" pos="adj" features="M=S" />
      <word_496 token="dia" lemma="dia" pos="n" features="M=S" />
      <word_497 token="19" lemma="" pos="num" features="M=P" />
    </sn>
  </Mencoes_Unicas>
</ConteudoXML>
